setup.py
fjnu/__init__.py
fjnu/api.py
fjnu/local.py
fjnu/operate.py
fjnu/schedule.py
fjnu/test.py
fjnu/xuexitong.py
fjnu.egg-info/PKG-INFO
fjnu.egg-info/SOURCES.txt
fjnu.egg-info/dependency_links.txt
fjnu.egg-info/requires.txt
fjnu.egg-info/top_level.txt
fjnu.egg-info/zip-safe