Metadata-Version: 1.1
Name: fjnu
Version: 0.1.8
Summary: 通过封装web api接口制作而成
Home-page: UNKNOWN
Author: listener
Author-email: 765934517@qq.com
License: MIT
Platform: UNKNOWN
Classifier: Programming Language :: Python
Classifier: Programming Language :: Python :: 3
Classifier: Programming Language :: Python :: 3.4
Classifier: Programming Language :: Python :: 3.5
Classifier: Programming Language :: Python :: 3.6
